LICENSE
MANIFEST.in
README.md
requirements.txt
setup.py
cartographi/__init__.py
cartographi/cli.py
cartographi/utils.py
cartographi.egg-info/PKG-INFO
cartographi.egg-info/SOURCES.txt
cartographi.egg-info/dependency_links.txt
cartographi.egg-info/entry_points.txt
cartographi.egg-info/not-zip-safe
cartographi.egg-info/requires.txt
cartographi.egg-info/top_level.txt
cartographi/config_validation/__init__.py
cartographi/config_validation/config_validator.py
cartographi/config_validation/mesh_schema.py
cartographi/config_validation/route_schema.py
cartographi/config_validation/vessel_schema.py
cartographi/config_validation/waypoints_schema.py
cartographi/dataloaders/__init__.py
cartographi/dataloaders/dataloader_interface.py
cartographi/dataloaders/factory.py
cartographi/dataloaders/scalar/__init__.py
cartographi/dataloaders/scalar/abstract_scalar.py
cartographi/dataloaders/scalar/amsr.py
cartographi/dataloaders/scalar/baltic_sea_ice.py
cartographi/dataloaders/scalar/bsose_depth.py
cartographi/dataloaders/scalar/bsose_sea_ice.py
cartographi/dataloaders/scalar/density.py
cartographi/dataloaders/scalar/era5_wave_height.py
cartographi/dataloaders/scalar/gebco.py
cartographi/dataloaders/scalar/icenet.py
cartographi/dataloaders/scalar/modis.py
cartographi/dataloaders/scalar/scalar_csv.py
cartographi/dataloaders/scalar/scalar_grf.py
cartographi/dataloaders/scalar/shape.py
cartographi/dataloaders/scalar/thickness.py
cartographi/dataloaders/vector/__init__.py
cartographi/dataloaders/vector/abstract_vector.py
cartographi/dataloaders/vector/baltic_current.py
cartographi/dataloaders/vector/duacs_current.py
cartographi/dataloaders/vector/era5_wave_direction.py
cartographi/dataloaders/vector/era5_wind.py
cartographi/dataloaders/vector/north_sea_current.py
cartographi/dataloaders/vector/oras5_current.py
cartographi/dataloaders/vector/sose.py
cartographi/dataloaders/vector/vector_csv.py
cartographi/dataloaders/vector/vector_grf.py
cartographi/mesh_generation/__init__.py
cartographi/mesh_generation/aggregated_cellbox.py
cartographi/mesh_generation/boundary.py
cartographi/mesh_generation/cellbox.py
cartographi/mesh_generation/direction.py
cartographi/mesh_generation/environment_mesh.py
