Metadata-Version: 2.1
Name: cartographi
Version: 1.0.3
Summary: CartograPhi: Earth's digital twin mapped on a non-uniform mesh
Home-page: https://www.github.com/antarctica
Author: Samuel Hall, George Coombs, Harrison Abbot, Ayat Fekry, Jonathan Smith, Maria Fox, James Byrne, Michael Thorne
Author-email: polarroute@bas.ac.uk
Maintainer: Samuel Hall, George Coombs, Harrison Abbot, Ayat Fekry, Jonathan Smith, Maria Fox, James Byrne, Michael Thorne
Maintainer-email: polarroute@bas.ac.uk
License: MIT
Classifier: 
Classifier: Development Status :: 3 - Alpha
Classifier: Intended Audience :: Science/Research
Classifier: Intended Audience :: System Administrators
Classifier: License :: OSI Approved :: MIT License
Classifier: Natural Language :: English
Classifier: Operating System :: OS Independent
Classifier: Programming Language :: Python
Classifier: Programming Language :: Python :: 3
Classifier: Programming Language :: Python :: 3.7
Classifier: Topic :: Scientific/Engineering
Classifier: 
Provides-Extra: tests
License-File: LICENSE
